{"examples_lovelace.md":"83bd5f1b","examples_overview.md":"f6ff2c63","examples_templates.md":"2a007fb9","guide_deployment-options.md":"1cd68646","guide_energy-management.md":"7646d86d","guide_fault-finding.md":"2c6e01fb","guide_getting-started.md":"f3c4326d","guide_overview.md":"b765ed35","guide_tested-inverters.md":"faffd5af","index.md":"ddbfe802","reference_definitions.md":"dd0b14a1","reference_definitions3ph.md":"646e9efc","reference_multi-options.md":"d7a718e7","reference_mysensors.md":"264de4e2","reference_sensor-modifiers.md":"171a0da3","guide_mbusd.md":"18f34361","examples_lovelace-settings.md":"16187f42","examples_a-mode.md":"d2fe3ce9"}
