{"examples_a-mode.md":"Cb0HS5J6","examples_lovelace-settings.md":"B7-RAcM7","examples_lovelace.md":"jv_74rIM","examples_overview.md":"BQla9p34","examples_templates.md":"D5ty1uyu","guide_deployment-options.md":"BH3FotpF","guide_energy-management.md":"C4MLqDRB","guide_esp.md":"CdeIgbRk","guide_fault-finding.md":"CVdzqTnh","guide_getting-started.md":"BR-Kwpty","guide_index.md":"BEplXV0v","guide_mbusd.md":"DEmm76JP","guide_overview.md":"BH_9nusQ","guide_standalone-deployment.md":"B-RHJd39","guide_tested-inverters.md":"Bsf6-rUy","guide_wiring.md":"BgKPKG4g","index.md":"BEfDlWGm","reference_definitions.md":"CmJDGqm4","reference_definitions3ph.md":"B6eAfqRt","reference_multi-options.md":"C7Y7v5Ht","reference_mysensors.md":"BaCBkPsO","reference_schedules.md":"CjWuAwm1","reference_sensor-modifiers.md":"oGfP79Gi"}
