{"examples_a-mode.md":"CmM-28-K","examples_lovelace-settings.md":"DFrRtS-k","examples_lovelace.md":"WJInB2FC","examples_overview.md":"CJnGbSkB","examples_templates.md":"8pj3qemc","guide_deployment-options.md":"Bo5oTmls","guide_energy-management.md":"5G7I5VLf","guide_esp.md":"qyJBv3Hx","guide_fault-finding.md":"D6aEEeEN","guide_getting-started.md":"BNEsACMX","guide_index.md":"BMZZ_fnj","guide_mbusd.md":"DIFrC_Ac","guide_overview.md":"DQVb91ga","guide_standalone-deployment.md":"C3Huv86n","guide_tested-inverters.md":"DxR1fR05","guide_wiring.md":"CYLe1yV-","index.md":"DyOHWYNm","reference_definitions.md":"CSF_kQL3","reference_definitions3ph.md":"BfwZZcN1","reference_multi-options.md":"CiZSjsol","reference_mysensors.md":"CqCBzV8D","reference_schedules.md":"CI-cx9jQ","reference_sensor-modifiers.md":"D5peIk4S"}
