{"reference_multi-options.md":"5da7b2e3","guide_deployment-options.md":"7132d6fd","guide_energy-management.md":"a4561e77","guide_tested-inverters.md":"a9ac0d6a","examples_a-mode.md":"6f533394","index.md":"c7bfbc7e","reference_definitions.md":"d729b57a","guide_mbusd.md":"b7e52787","guide_fault-finding.md":"be1b85b7","guide_getting-started.md":"d1ea4786","reference_mysensors.md":"0fa20b52","examples_templates.md":"fc557dbf","guide_intro.md":"6a867bf2","examples_ll-power.md":"cd98f0c9","reference_definitions3ph.md":"b12d400e","reference_sensor-modifiers.md":"32c01400","examples_ll-settings.md":"7d8168c4","examples_overview.md":"1f5d1e24"}
