{"guide_overview.md":"CNS9CgEv","guide_energy-management.md":"BQuQZkoC","guide_tested-inverters.md":"CUTFGF0f","examples_overview.md":"V8yeXAJz","reference_schedules.md":"DldtRo9I","guide_mbusd.md":"DA9pQtfS","guide_standalone-deployment.md":"BQ4sqt-U","guide_deployment-options.md":"krgyGOUi","examples_lovelace-settings.md":"8F9XW3eP","examples_a-mode.md":"Cub25mmZ","reference_multi-options.md":"kTfGyr8Y","examples_esp.md":"dqY9bJHw","reference_mysensors.md":"B6q-B_F-","guide_wiring.md":"BBH03WDC","guide_index.md":"GlH7bMuc","guide_getting-started.md":"m2HDkLWJ","reference_sensor-modifiers.md":"xVxf5oIC","reference_definitions3ph.md":"DT18W0Hk","index.md":"Dpgu3XIu","reference_definitions.md":"DFAkIjVu","guide_fault-finding.md":"gl-hGje8","examples_templates.md":"Bxpid3-T","examples_lovelace.md":"C6ZDyYXo"}
